dpt/__init__.py
dpt/management.py
dpt/processor.py
dpt/storage.py
dpt/deployment/__init__.py
dpt/deployment/common.py
dpt/deployment/deploy.py
dpt/deployment/extract.py
dpt/mongo/__init__.py
dpt/mongo/commands.py
dpt/mongo/files.py
dpt-1.2.3.dist-info/METADATA
dpt-1.2.3.dist-info/WHEEL
dpt-1.2.3.dist-info/top_level.txt
dpt-1.2.3.dist-info/RECORD
