Metadata-Version: 2.1
Name: dpt
Version: 1.2.3
Summary: UNKNOWN
Home-page: UNKNOWN
Author: DF
Author-email: your_email@example.com
License: UNKNOWN
Platform: UNKNOWN
Requires-Dist: GitPython >=3.1.41
Requires-Dist: pymongo >=4.6.1
Requires-Dist: jsonschema >=4.6.0
